ppslack/__init__.py
ppslack/__main__.py
ppslack/__version__.py
ppslack/main.py
ppslack/slack.py
ppslack-4.0.2.dist-info/licenses/LICENSE.txt
ppslack-4.0.2.dist-info/METADATA
ppslack-4.0.2.dist-info/WHEEL
ppslack-4.0.2.dist-info/entry_points.txt
ppslack-4.0.2.dist-info/top_level.txt
ppslack-4.0.2.dist-info/RECORD
