Metadata-Version: 2.4
Name: ppslack
Version: 4.0.2
Summary: Tool to send Slack messages
Author-email: Peter Pakos <peter@pakos.uk>
License: GPLv3
Project-URL: GitHub, https://github.com/peterpakos/ppslack/
Project-URL: PyPI, https://pypi.org/project/ppslack/
Keywords: slack,message,notification,notify
Classifier: Programming Language :: Python :: 3
Classifier: Programming Language :: Python :: 3.7
Classifier: Programming Language :: Python :: 3.8
Classifier: Programming Language :: Python :: 3.9
Classifier: Programming Language :: Python :: 3.10
Classifier: Programming Language :: Python :: 3.11
Classifier: License :: OSI Approved :: GNU General Public License v3 (GPLv3)
Classifier: Topic :: Communications :: Chat
Requires-Python: >=3.7
License-File: LICENSE.txt
Requires-Dist: pplogger
Requires-Dist: ppconfig
Requires-Dist: slack_sdk
Dynamic: license-file
